llll/__init__.py
llll_py-0.1.0.dist-info/METADATA
llll_py-0.1.0.dist-info/WHEEL
llll_py-0.1.0.dist-info/licenses/LICENSE
llll_py-0.1.0.dist-info/RECORD
