Metadata-Version: 2.4
Name: llll-py
Version: 0.1.0
Summary: A basic package for parsing lisp-like linked lists in Python.
License-File: LICENSE
Author: Felipe Tovar-Henao
Author-email: pipetovarh@hotmail.com
Requires-Python: >=3.12
Classifier: Programming Language :: Python :: 3
Classifier: Programming Language :: Python :: 3.12
Classifier: Programming Language :: Python :: 3.13
Classifier: Programming Language :: Python :: 3.14
